ciffmbd2016mcegln/__init__.py
ciffmbd2016mcegln-14.0.3.dist-info/DESCRIPTION.rst
ciffmbd2016mcegln-14.0.3.dist-info/METADATA
ciffmbd2016mcegln-14.0.3.dist-info/RECORD
ciffmbd2016mcegln-14.0.3.dist-info/WHEEL
ciffmbd2016mcegln-14.0.3.dist-info/metadata.json
ciffmbd2016mcegln-14.0.3.dist-info/top_level.txt
