Metadata-Version: 2.0
Name: ciffmbd2016mcegln
Version: 14.0.3
Summary: Autopredict libaries from mat4os
Home-page: https://github.com/mat4os/autopredict
Author: mat4os
Author-email: mat4os@gmx.es
License: MIT
Platform: UNKNOWN
